PyShare/PyShare.py
PyShare/__init__.py
PyShare/share-threading.jar
PyShareTesting2-0.7.dist-info/METADATA
PyShareTesting2-0.7.dist-info/WHEEL
PyShareTesting2-0.7.dist-info/top_level.txt
PyShareTesting2-0.7.dist-info/RECORD
