Metadata-Version: 2.1
Name: PyShareTesting2
Version: 0.7
Summary: An example of a python package from pre-existing code
Home-page: UNKNOWN
Author: UNKNOWN
Author-email: UNKNOWN
License: MIT
Platform: UNKNOWN
